bgpsimulator/__init__.py
bgpsimulator/__main__.py
bgpsimulator/py.typed
bgpsimulator/as_graphs/__init__.py
bgpsimulator/as_graphs/as_graph/__init__.py
bgpsimulator/as_graphs/as_graph/as_graph.py
bgpsimulator/as_graphs/as_graph/as_graph_utils.py
bgpsimulator/as_graphs/as_graph/base_as.py
bgpsimulator/as_graphs/as_graph_generators/__init__.py
bgpsimulator/as_graphs/as_graph_generators/caida/__init__.py
bgpsimulator/as_graphs/as_graph_generators/caida/caida_as_graph_collector.py
bgpsimulator/as_graphs/as_graph_generators/caida/caida_as_graph_json_converter.py
bgpsimulator/engine_runner/__init__.py
bgpsimulator/engine_runner/diagram.py
bgpsimulator/engine_runner/engine_run_config.py
bgpsimulator/engine_runner/engine_runner.py
bgpsimulator/route_validator/__init__.py
bgpsimulator/route_validator/roa.py
bgpsimulator/route_validator/roas_node.py
bgpsimulator/route_validator/route_validator.py
bgpsimulator/shared/__init__.py
bgpsimulator/shared/constants.py
bgpsimulator/shared/enums.py
bgpsimulator/shared/exceptions.py
bgpsimulator/shared/ip_addr.py
bgpsimulator/shared/policy_propagate_info.py
bgpsimulator/shared/prefix.py
bgpsimulator/simulation_engine/__init__.py
bgpsimulator/simulation_engine/announcement.py
bgpsimulator/simulation_engine/simulation_engine.py
bgpsimulator/simulation_engine/policy/__init__.py
bgpsimulator/simulation_engine/policy/adj_ribs_in.py
bgpsimulator/simulation_engine/policy/adj_ribs_out.py
bgpsimulator/simulation_engine/policy/policy.py
bgpsimulator/simulation_engine/policy/policy_extensions/__init__.py
bgpsimulator/simulation_engine/policy/policy_extensions/announce_then_withdraw.py
bgpsimulator/simulation_engine/policy/policy_extensions/as_path_edge_filter.py
bgpsimulator/simulation_engine/policy/policy_extensions/aspa.py
bgpsimulator/simulation_engine/policy/policy_extensions/aspapp.py
bgpsimulator/simulation_engine/policy/policy_extensions/aspawn.py
bgpsimulator/simulation_engine/policy/policy_extensions/asra.py
bgpsimulator-0.2.7.dist-info/licenses/LICENSE.txt
bgpsimulator-0.2.7.dist-info/METADATA
bgpsimulator-0.2.7.dist-info/WHEEL
bgpsimulator-0.2.7.dist-info/entry_points.txt
bgpsimulator-0.2.7.dist-info/top_level.txt
bgpsimulator-0.2.7.dist-info/RECORD
