Metadata-Version: 2.4
Name: bgpsimulator
Version: 0.2.7
Summary: Simulates BGP, ROV, ASPA, etc in an extensible manner
Author-email: Justin Furuness <jfuruness@gmail.com>
Maintainer-email: Justin Furuness <jfuruness@gmail.com>
License: Copyright 2025 Justin Furuness
Project-URL: Homepage, https://github.com/jfuruness/bgpsimulator
Project-URL: Documentation, https://github.com/jfuruness/bgpsimulator
Keywords: bgpsimulator,BGPy,bgpy,bgpc,bgpy_pkg,BGP,Caida,CAIDA,Peers,Providers,Relationships,AS-Serial,Customers,Simulation,ROV,Furuness
Classifier: Programming Language :: Python :: 3.10
Classifier: Programming Language :: Python :: 3.11
Classifier: Programming Language :: Python :: 3.12
Classifier: Programming Language :: Python :: 3.13
Classifier: Programming Language :: Python :: Implementation :: CPython
Classifier: Programming Language :: Python :: Implementation :: PyPy
Classifier: Environment :: Console
Classifier: Intended Audience :: Developers
Classifier: Operating System :: POSIX :: Linux
Classifier: Operating System :: MacOS
Classifier: Operating System :: MacOS :: MacOS X
Classifier: Topic :: Security
Requires-Python: >=3.11
License-File: LICENSE.txt
Requires-Dist: beautifulsoup4~=4.0
Requires-Dist: frozendict~=2.0
Requires-Dist: graphviz~=0.21
Requires-Dist: matplotlib==3.10.3
Requires-Dist: platformdirs~=4.0
Requires-Dist: psutil~=7.0
Requires-Dist: requests~=2.0
Requires-Dist: requests-cache~=1.0
Requires-Dist: tqdm~=4.0
Provides-Extra: test
Requires-Dist: pytest~=8.0; extra == "test"
Requires-Dist: pre-commit~=4.0; extra == "test"
Requires-Dist: types-beautifulsoup4~=4.0; extra == "test"
Requires-Dist: types-requests~=2.0; extra == "test"
Requires-Dist: types-psutil~=6.0; extra == "test"
Requires-Dist: types-tqdm~=4.0; extra == "test"
Requires-Dist: mypy~=1.0; extra == "test"
Requires-Dist: flake8~=7.0; extra == "test"
Requires-Dist: tox~=4.0; extra == "test"
Requires-Dist: pytest-xdist~=3.0; extra == "test"
Requires-Dist: ruff; extra == "test"
Dynamic: license-file
